requirements.txt
setup.py
dist/ella-filer-galleries-1.0.0.tar.gz
ella_filer_galleries/__init__.py
ella_filer_galleries/conf.py
ella_filer_galleries/models.py
ella_filer_galleries.egg-info/PKG-INFO
ella_filer_galleries.egg-info/SOURCES.txt
ella_filer_galleries.egg-info/dependency_links.txt
ella_filer_galleries.egg-info/requires.txt
ella_filer_galleries.egg-info/top_level.txt