Metadata-Version: 1.1
Name: ella-filer-galleries
Version: 1.0.0
Summary: Link Ella galleries to the django-filer folders.
Home-page: http://github.com/xaralis/ella-filer-galleries
Author: Filip Varecha
Author-email: xaralis@centrum.cz
License: BSD
Platform: UNKNOWN
Classifier: Development Status :: 4 - Beta
Classifier: Intended Audience :: Developers
Classifier: License :: OSI Approved :: BSD License
Classifier: Operating System :: OS Independent
Classifier: Framework :: Django
Classifier: Programming Language :: Python :: 2.5
Classifier: Programming Language :: Python :: 2.6
Classifier: Programming Language :: Python :: 2.7
Classifier: Operating System :: OS Independent
Classifier: Topic :: Internet :: WWW/HTTP :: Dynamic Content
Classifier: Topic :: Software Development :: Libraries :: Python Modules
